grafgate/__init__.py
grafgate/grafgate.py
grafgate/schemas.py
grafgate-0.0.1.dist-info/METADATA
grafgate-0.0.1.dist-info/WHEEL
grafgate-0.0.1.dist-info/top_level.txt
grafgate-0.0.1.dist-info/RECORD
