Metadata-Version: 2.1
Name: grafgate
Version: 0.0.1
Summary: Toolkit for building Grafana data source backend
Home-page: https://github.com/akopkesheshyan/grafgate
Author: Akop Kesheshyan
Author-email: hello@akop.dev
License: MIT
Platform: any
Classifier: Development Status :: 4 - Beta
Classifier: Intended Audience :: Developers
Classifier: License :: OSI Approved :: MIT License
Classifier: Operating System :: POSIX
Classifier: Programming Language :: Python
Classifier: Topic :: Software Development :: Libraries
Requires-Dist: aiohttp
Requires-Dist: pydantic
Provides-Extra: dev
Requires-Dist: flake8 ; extra == 'dev'
Requires-Dist: safety ; extra == 'dev'
Requires-Dist: pydocstyle ; extra == 'dev'
Requires-Dist: piprot ; extra == 'dev'
Requires-Dist: pytest ; extra == 'dev'
Requires-Dist: pytest-cov ; extra == 'dev'
Requires-Dist: pytest-asyncio ; extra == 'dev'
